meteofrance/__init__.py
meteofrance/__main__.py
meteofrance/client.py
meteofrance-0.3.8.dist-info/LICENSE
meteofrance-0.3.8.dist-info/METADATA
meteofrance-0.3.8.dist-info/WHEEL
meteofrance-0.3.8.dist-info/top_level.txt
meteofrance-0.3.8.dist-info/RECORD
