Metadata-Version: 2.1
Name: meteofrance
Version: 0.3.8
Summary: Meteo-France weather forecast
Home-page: https://github.com/victorcerutti/meteofrance-py
Author: victorcerutti
Author-email: victorcerutti+meteofrance@gmail.com
License: MIT
Platform: UNKNOWN
Requires-Dist: requests
Requires-Dist: beautifulsoup4
Requires-Dist: pytz
